supabase_auth/__init__.py
supabase_auth/_async/__init__.py
supabase_auth/_async/gotrue_admin_api.py
supabase_auth/_async/gotrue_admin_mfa_api.py
supabase_auth/_async/gotrue_admin_oauth_api.py
supabase_auth/_async/gotrue_base_api.py
supabase_auth/_async/gotrue_client.py
supabase_auth/_async/gotrue_mfa_api.py
supabase_auth/_async/storage.py
supabase_auth/_sync/__init__.py
supabase_auth/_sync/gotrue_admin_api.py
supabase_auth/_sync/gotrue_admin_mfa_api.py
supabase_auth/_sync/gotrue_admin_oauth_api.py
supabase_auth/_sync/gotrue_base_api.py
supabase_auth/_sync/gotrue_client.py
supabase_auth/_sync/gotrue_mfa_api.py
supabase_auth/_sync/storage.py
supabase_auth/constants.py
supabase_auth/errors.py
supabase_auth/helpers.py
supabase_auth/http_clients.py
supabase_auth/py.typed
supabase_auth/timer.py
supabase_auth/types.py
supabase_auth/version.py
supabase_auth-2.23.1.dist-info/WHEEL
supabase_auth-2.23.1.dist-info/METADATA
supabase_auth-2.23.1.dist-info/RECORD
