Metadata-Version: 2.4
Name: supabase-auth
Version: 2.23.1
Summary: Python Client Library for Supabase Auth
Author: Joel Lee
Author-email: Joel Lee <joel@joellee.org>
License-Expression: MIT
Classifier: Programming Language :: Python :: 3
Classifier: License :: OSI Approved :: MIT License
Classifier: Operating System :: OS Independent
Requires-Dist: httpx[http2]>=0.26,<0.29
Requires-Dist: pydantic>=1.10,<3
Requires-Dist: pyjwt[crypto]>=2.10.1
Maintainer: Leonardo Santiago
Maintainer-email: Leonardo Santiago <leonardo.santiago@supabase.io>
Requires-Python: >=3.9
Project-URL: changelog, https://github.com/supabase/supabase-py/tree/main/CHANGELOG.md
Project-URL: documentation, https://github.com/supabase/supabase-py/tree/main/src/auth
Project-URL: homepage, https://github.com/supabase/supabase-py/tree/main/src/auth
Project-URL: repository, https://github.com/supabase/supabase-py
